README.txt
setup.py
DisplayShelf.egg-info/PKG-INFO
DisplayShelf.egg-info/SOURCES.txt
DisplayShelf.egg-info/dependency_links.txt
DisplayShelf.egg-info/entry_points.txt
DisplayShelf.egg-info/not-zip-safe
DisplayShelf.egg-info/paster_plugins.txt
DisplayShelf.egg-info/requires.txt
DisplayShelf.egg-info/sqlobject.txt
DisplayShelf.egg-info/top_level.txt
displayshelf/__init__.py
displayshelf/release.py
displayshelf/widgets.py
displayshelf/templates/__init__.py
