Metadata-Version: 1.0
Name: DisplayShelf
Version: 1.0
Summary: The Flex Display Shelf
Home-page: UNKNOWN
Author: James Ward and Kevin Dangoor
Author-email: james@jamesward.org kid@blazingthings.com
License: MIT
Keywords: turbogears.widgets
Platform: UNKNOWN
Classifier: Development Status :: 3 - Alpha
Classifier: Operating System :: OS Independent
Classifier: Programming Language :: Python
Classifier: Topic :: Software Development :: Libraries :: Python Modules
Classifier: Framework :: TurboGears
Classifier: Framework :: TurboGears :: Widgets
